prinder/__init__.py
prinder/logger.py
prinder/notifiers.py
prinder/prinder.py
prinder/pull_reminder.py
prinder/utilities.py
prinder/notifiers/__init__.py
prinder/notifiers/base_notifier.py
prinder/notifiers/mail_notifier.py
prinder/notifiers/slack_notifier.py
prinder/notifiers/templates/__init__.py
prinder/notifiers/templates/mail_template.html
prinder/notifiers/templates/slack_template.template
prinder-1.2.2.dist-info/METADATA
prinder-1.2.2.dist-info/RECORD
prinder-1.2.2.dist-info/WHEEL
prinder-1.2.2.dist-info/entry_points.txt
prinder-1.2.2.dist-info/top_level.txt
