Metadata-Version: 2.1
Name: prinder
Version: 1.2.2
Summary: Posts a list of open pull requests for an organization
Home-page: http://github.com/masterlittle/Prinder
Author: Shitij Goyal
Author-email: goyalshitij@gmail.com
License: MIT
Platform: UNKNOWN
Classifier: Programming Language :: Python :: 2.7
Classifier: License :: OSI Approved :: MIT License
Requires-Dist: Jinja2 (==2.10)
Requires-Dist: MarkupSafe (==1.0)
Requires-Dist: asn1crypto (==0.24.0)
Requires-Dist: certifi (==2018.4.16)
Requires-Dist: cffi (==1.11.5)
Requires-Dist: chardet (==3.0.4)
Requires-Dist: click (==6.7)
Requires-Dist: cryptography (==2.2.2)
Requires-Dist: enum34 (==1.1.6)
Requires-Dist: github3.py (==1.1.0)
Requires-Dist: idna (==2.7)
Requires-Dist: ipaddress (==1.0.22)
Requires-Dist: ndg-httpsclient (==0.5.0)
Requires-Dist: pyasn1 (==0.4.3)
Requires-Dist: pycparser (==2.18)
Requires-Dist: pyOpenSSL (==18.0.0)
Requires-Dist: python-dateutil (==2.7.3)
Requires-Dist: PyYAML (==3.13)
Requires-Dist: requests (==2.19.1)
Requires-Dist: six (==1.11.0)
Requires-Dist: slacker (==0.9.65)
Requires-Dist: uritemplate (==3.0.0)
Requires-Dist: urllib3 (==1.23)
